python_bootstrap/__init__.py
python_bootstrap/main.py
python_bootstrap-0.0.5.dist-info/LICENSE
python_bootstrap-0.0.5.dist-info/METADATA
python_bootstrap-0.0.5.dist-info/WHEEL
python_bootstrap-0.0.5.dist-info/top_level.txt
python_bootstrap-0.0.5.dist-info/RECORD
