Metadata-Version: 2.1
Name: python-bootstrap
Version: 0.0.5
Summary: python-bootstrap package
Home-page: https://github.com/wix-private/hdc3/tree/master/apps-py/wixfra
Author: Alex Shemshurenko
Author-email: alexshe@wix.com
License: Apache License Version 2
Platform: UNKNOWN
Classifier: Programming Language :: Python :: 3.7
Classifier: License :: OSI Approved :: MIT License
Classifier: Operating System :: OS Independent
Requires-Python: >=3.7
